autoappanalysis/Controller.py
autoappanalysis/__init__.py
autoappanalysis/__main__.py
autoappanalysis/cmd/HostCommand.py
autoappanalysis/cmd/VirtualBoxCommand.py
autoappanalysis/cmd/__init__.py
autoappanalysis/gui/Gui.py
autoappanalysis/gui/__init__.py
autoappanalysis/processor/Processor.py
autoappanalysis/processor/__init__.py
autoappanalysis-2.1.0.dist-info/LICENSE.md
autoappanalysis-2.1.0.dist-info/METADATA
autoappanalysis-2.1.0.dist-info/WHEEL
autoappanalysis-2.1.0.dist-info/entry_points.txt
autoappanalysis-2.1.0.dist-info/top_level.txt
autoappanalysis-2.1.0.dist-info/RECORD
