Metadata-Version: 2.1
Name: autoappanalysis
Version: 2.1.0
Summary: Automation GUI for Android App Analysis
Home-page: https://github.com/5f0ne/autoappanalysis
Author: 5f0
License: MIT
Classifier: Operating System :: OS Independent 
Classifier: Programming Language :: Python :: 3 
Classifier: License :: OSI Approved :: MIT License 
License-File: LICENSE.md
